tplink_smarthome/__init__.py
tplink_smarthome/device.py
tplink_smarthome/plug.py
tplink_smarthome/protocol.py
tplink_smarthome/version.py
python_tplink_smarthome-0.1.3.dist-info/LICENSE
python_tplink_smarthome-0.1.3.dist-info/METADATA
python_tplink_smarthome-0.1.3.dist-info/WHEEL
python_tplink_smarthome-0.1.3.dist-info/top_level.txt
python_tplink_smarthome-0.1.3.dist-info/RECORD
