Metadata-Version: 2.1
Name: python-tplink-smarthome
Version: 0.1.3
Summary: A package to communicate with TP-Link smart devices.
Home-page: https://github.com/j-muller/python-tplink-smarthome
Author: Jeffrey Muller
Author-email: jeffrey.muller92@gmail.com
License: UNKNOWN
Platform: UNKNOWN
Classifier: Programming Language :: Python :: 3.5
